LICENSE
iclingo/__init__.py
iclingo/__main__.py
iclingo/install.py
iclingo/interface.py
iclingo/kernel.py
iclingo-0.1.7.dist-info/LICENSE
iclingo-0.1.7.dist-info/WHEEL
iclingo-0.1.7.dist-info/METADATA
iclingo-0.1.7.dist-info/RECORD
